randomtimestamp/__init__.py
randomtimestamp/__main__.py
randomtimestamp/core.py
randomtimestamp/functions.py
randomtimestamp-2.3.dist-info/METADATA
randomtimestamp-2.3.dist-info/WHEEL
randomtimestamp-2.3.dist-info/entry_points.txt
randomtimestamp-2.3.dist-info/top_level.txt
randomtimestamp-2.3.dist-info/RECORD
