Metadata-Version: 2.1
Name: randomtimestamp
Version: 2.3
Summary: Generate random time stamps
Home-page: https://github.com/ByteBaker/randomtimestamp
Author: ByteBaker
Author-email: 42913098+ByteBaker@users.noreply.github.com
License: GPL v3.0
Classifier: License :: OSI Approved :: GNU General Public License v3 (GPLv3)
Classifier: Operating System :: OS Independent
Classifier: Programming Language :: Python :: 3.13
Classifier: Development Status :: 5 - Production/Stable
